{
    "backup-dir": "H:\\windows-backup",
    "applications":
    {
        "general":
        [
            "%userprofile%\\Documents\\facility-data",
            "%userprofile%\\Documents\\My Games\\Test Bank",
            "%userprofile%\\Documents\\opentrack-2.3",
            "%userprofile%\\Documents\\Programming",
            "%userprofile%\\Documents\\scope",
            "%userprofile%\\Documents\\VRC",
            "%userprofile%\\Music\\"
        ],
        "Microsoft":
        [
            "%localappdata%\\Microsoft\\Edge\\User Data\\Default"
        ],
        "PowerToys":
        [
            "%localappdata%\\Microsoft\\PowerToys",
            "%userprofile%\\AppData\\LocalLow\\Microsoft\\PowerToys",
            "%userprofile%\\Documents\\PowerToys"
        ],
        "MSIAfterburner":
        [
            "C:\\Program Files (x86)\\MSI Afterburner\\Profiles"
        ],
        "Intel Extreme Tuning Utility":
        [
            "C:\\ProgramData\\Intel\\Intel Extreme Tuning Utility",
        "%programdata%\\Intel\\Intel Extreme Tuning Utility"
        ]
        ,
        ".minecraft":
        [
            "%appdata%\\.minecraft\\launcher_settings.json",
            "%appdata%\\.minecraft\\launcher_ui_state_microsoft_store.json",
            "%appdata%\\.minecraft\\mods",
            "%appdata%\\.minecraft\\options.txt",
            "%appdata%\\.minecraft\\optionsof.txt",
            "%appdata%\\.minecraft\\optionsshaders.txt",
            "%appdata%\\.minecraft\\resourcepacks",
            "%appdata%\\.minecraft\\saves",
            "%appdata%\\.minecraft\\screenshots",
            "%appdata%\\.minecraft\\servers.dat",
            "%appdata%\\.minecraft\\shaderpacks"
        ],
        "Adobe":
        [
            "%appdata%\\Adobe\\Acrobat",
            "%appdata%\\Adobe\\Adobe PDF",
            "%appdata%\\Adobe\\Color",
            "%localappdata%\\Adobe",
            "%programdata%\\Adobe"
        ],
        "Apple Computer":
        [
            "%appdata%\\Apple Computer\\iTunes",
            "%appdata%\\Apple Computer\\Preferences"
        ],
        "AutoDarkMode":
        [
            "%appdata%\\AutoDarkMode",
            "%localappdata%\\AutoDarkMode"
        ],
        "Blackmagic Design":
        [
            "%appdata%\\Blackmagic Design\\DaVinci Resolve\\Preferences",
            "%programdata%\\Blackmagic Design"
        ],
        "Canon_Inc_IC":
        [
            "%appdata%\\Canon_Inc_IC\\DPP4\\DppMWare\\settings.bin"
        ],
        "Cherry":
        [
            "%appdata%\\Cherry"
        ],
        "com.towercab.viewer":
        [
            "%appdata%\\com.towercab.viewer"
        ],
        "CRC":
        [
            "%localappdata%\\CRC"
        ],
        "discord":
        [
            "%appdata%\\discord"
        ],
        "Dropbox":
        [
            "%appdata%\\Dropbox"
        ],
        "elevatex":
        [
            "%appdata%\\elevatex"
        ],
        "EuroScope":
        [
            "%appdata%\\EuroScope"
        ],
        "jupyter":
        [
            "%appdata%\\jupyter",
            "%userprofile%\\.jupyter"
        ],
        "logioptionsplus":
        [
            "%appdata%\\logioptionsplus",
            "%localappdata%\\LogiOptionsPlus"
        ],
        "Microsoft Flight Simulator":
        [
            "%appdata%\\Microsoft Flight Simulator"
        ],
        "Mozilla":
        [
            "%appdata%\\Mozilla"
        ],
        "neat":
        [
            "%appdata%\\neat"
        ],
        "NVIDIA":
        [
            "%localappdata%\\NVIDIA Corporation",
            "%programdata%\\NVIDIA Corporation"
        ],
        "obs-studio":
        [
            "%appdata%\\obs-studio"
        ],
        "org.vatsim.vatis":
        [
            "%localappdata%\\org.vatsim.vatis"
        ],
        "org.vatsim.xpilot":
        [
            "%localappdata%\\org.vatsim.xpilot"
        ],
        "Python":
        [
            "%appdata%\\Python"
        ],
        "QGIS":
        [
            "%appdata%\\QGIS"
        ],
        "Sublime Text 3":
        [
            "%appdata%\\Sublime Text 3"
        ],
        "TeamSpeak":
        [
            "%appdata%\\TeamSpeak",
            "%appdata%\\TS3Client"
        ],
        "Toolkit":
        [
            "%appdata%\\Toolkit"
        ],
        "uTorrent":
        [
            "%appdata%\\uTorrent"
        ],
        "vERAM":
        [
            "%localappdata%\\vERAM"
        ],
        "vPilot":
        [
            "%localappdata%\\vPilot"
        ],
        "Volanta":
        [
            "%appdata%\\Volanta"
        ],
        "vSTARS":
        [
            "%appdata%\\vSTARS"
        ],
        "X-Plane":
        [
            "%appdata%\\X-Plane"
        ]
    }
}